astrosource/__init__.py
astrosource/analyse.py
astrosource/astrosource.py
astrosource/bug_test.py
astrosource/comparison.py
astrosource/detrend.py
astrosource/eebls.py
astrosource/identify.py
astrosource/main.py
astrosource/periodic.py
astrosource/plots.py
astrosource/utils.py
astrosource/test/__init__.py
astrosource/test/mocks.py
astrosource/test/test_comparison.py
astrosource/test/test_identify.py
astrosource/test/test_period.py
astrosource-1.8.1.dist-info/licenses/LICENCE.txt
astrosource-1.8.1.dist-info/METADATA
astrosource-1.8.1.dist-info/WHEEL
astrosource-1.8.1.dist-info/entry_points.txt
astrosource-1.8.1.dist-info/top_level.txt
astrosource-1.8.1.dist-info/RECORD
