Metadata-Version: 2.4
Name: astrosource
Version: 1.8.1
Summary: Analysis script for sources with variability in their brightness
Author-email: Michael Fitzgerald <info@realpython.com>, Edward Gomez <egomez@lco.global>
Project-URL: Homepage, https://github.com/zemogle/astrosource
Keywords: astronomy,time-series,analysis
Classifier: License :: OSI Approved :: MIT License
Classifier: Programming Language :: Python
Classifier: Programming Language :: Python :: 3
Requires-Python: >=3.7
License-File: LICENCE.txt
Requires-Dist: astropy>=4.3.1
Requires-Dist: astroquery
Requires-Dist: barycorrpy
Requires-Dist: beautifulsoup4
Requires-Dist: click
Requires-Dist: colorlog
Requires-Dist: matplotlib
Requires-Dist: numpy>=1.17
Requires-Dist: prettytable
Provides-Extra: dev
Requires-Dist: pytest; extra == "dev"
Dynamic: license-file
